[
  {
    "NOK_per_kWh": 1.12621,
    "EUR_per_kWh": 0.09889,
    "EXR": 11.3885,
    "time_start": "2026-02-03T00:00:00+01:00",
    "time_end": "2026-02-03T01:00:00+01:00"
  },
  {
    "NOK_per_kWh": 1.10992,
    "EUR_per_kWh": 0.09746,
    "EXR": 11.3885,
    "time_start": "2026-02-03T01:00:00+01:00",
    "time_end": "2026-02-03T02:00:00+01:00"
  },
  {
    "NOK_per_kWh": 1.08475,
    "EUR_per_kWh": 0.09525,
    "EXR": 11.3885,
    "time_start": "2026-02-03T02:00:00+01:00",
    "time_end": "2026-02-03T03:00:00+01:00"
  },
  {
    "NOK_per_kWh": 1.06779,
    "EUR_per_kWh": 0.09376,
    "EXR": 11.3885,
    "time_start": "2026-02-03T03:00:00+01:00",
    "time_end": "2026-02-03T04:00:00+01:00"
  },
  {
    "NOK_per_kWh": 1.06175,
    "EUR_per_kWh": 0.09323,
    "EXR": 11.3885,
    "time_start": "2026-02-03T04:00:00+01:00",
    "time_end": "2026-02-03T05:00:00+01:00"
  },
  {
    "NOK_per_kWh": 1.12336,
    "EUR_per_kWh": 0.09864,
    "EXR": 11.3885,
    "time_start": "2026-02-03T05:00:00+01:00",
    "time_end": "2026-02-03T06:00:00+01:00"
  },
  {
    "NOK_per_kWh": 1.28644,
    "EUR_per_kWh": 0.11296,
    "EXR": 11.3885,
    "time_start": "2026-02-03T06:00:00+01:00",
    "time_end": "2026-02-03T07:00:00+01:00"
  },
  {
    "NOK_per_kWh": 1.48836,
    "EUR_per_kWh": 0.13069,
    "EXR": 11.3885,
    "time_start": "2026-02-03T07:00:00+01:00",
    "time_end": "2026-02-03T08:00:00+01:00"
  },
  {
    "NOK_per_kWh": 1.94903,
    "EUR_per_kWh": 0.17114,
    "EXR": 11.3885,
    "time_start": "2026-02-03T08:00:00+01:00",
    "time_end": "2026-02-03T09:00:00+01:00"
  },
  {
    "NOK_per_kWh": 1.67286,
    "EUR_per_kWh": 0.14689,
    "EXR": 11.3885,
    "time_start": "2026-02-03T09:00:00+01:00",
    "time_end": "2026-02-03T10:00:00+01:00"
  },
  {
    "NOK_per_kWh": 1.4042,
    "EUR_per_kWh": 0.1233,
    "EXR": 11.3885,
    "time_start": "2026-02-03T10:00:00+01:00",
    "time_end": "2026-02-03T11:00:00+01:00"
  },
  {
    "NOK_per_kWh": 1.3402,
    "EUR_per_kWh": 0.11768,
    "EXR": 11.3885,
    "time_start": "2026-02-03T11:00:00+01:00",
    "time_end": "2026-02-03T12:00:00+01:00"
  },
  {
    "NOK_per_kWh": 1.30581,
    "EUR_per_kWh": 0.11466,
    "EXR": 11.3885,
    "time_start": "2026-02-03T12:00:00+01:00",
    "time_end": "2026-02-03T13:00:00+01:00"
  },
  {
    "NOK_per_kWh": 1.30979,
    "EUR_per_kWh": 0.11501,
    "EXR": 11.3885,
    "time_start": "2026-02-03T13:00:00+01:00",
    "time_end": "2026-02-03T14:00:00+01:00"
  },
  {
    "NOK_per_kWh": 1.30489,
    "EUR_per_kWh": 0.11458,
    "EXR": 11.3885,
    "time_start": "2026-02-03T14:00:00+01:00",
    "time_end": "2026-02-03T15:00:00+01:00"
  },
  {
    "NOK_per_kWh": 1.30011,
    "EUR_per_kWh": 0.11416,
    "EXR": 11.3885,
    "time_start": "2026-02-03T15:00:00+01:00",
    "time_end": "2026-02-03T16:00:00+01:00"
  },
  {
    "NOK_per_kWh": 1.34851,
    "EUR_per_kWh": 0.11841,
    "EXR": 11.3885,
    "time_start": "2026-02-03T16:00:00+01:00",
    "time_end": "2026-02-03T17:00:00+01:00"
  },
  {
    "NOK_per_kWh": 1.4493,
    "EUR_per_kWh": 0.12726,
    "EXR": 11.3885,
    "time_start": "2026-02-03T17:00:00+01:00",
    "time_end": "2026-02-03T18:00:00+01:00"
  },
  {
    "NOK_per_kWh": 1.40329,
    "EUR_per_kWh": 0.12322,
    "EXR": 11.3885,
    "time_start": "2026-02-03T18:00:00+01:00",
    "time_end": "2026-02-03T19:00:00+01:00"
  },
  {
    "NOK_per_kWh": 1.35284,
    "EUR_per_kWh": 0.11879,
    "EXR": 11.3885,
    "time_start": "2026-02-03T19:00:00+01:00",
    "time_end": "2026-02-03T20:00:00+01:00"
  },
  {
    "NOK_per_kWh": 1.28212,
    "EUR_per_kWh": 0.11258,
    "EXR": 11.3885,
    "time_start": "2026-02-03T20:00:00+01:00",
    "time_end": "2026-02-03T21:00:00+01:00"
  },
  {
    "NOK_per_kWh": 1.21754,
    "EUR_per_kWh": 0.10691,
    "EXR": 11.3885,
    "time_start": "2026-02-03T21:00:00+01:00",
    "time_end": "2026-02-03T22:00:00+01:00"
  },
  {
    "NOK_per_kWh": 1.19682,
    "EUR_per_kWh": 0.10509,
    "EXR": 11.3885,
    "time_start": "2026-02-03T22:00:00+01:00",
    "time_end": "2026-02-03T23:00:00+01:00"
  },
  {
    "NOK_per_kWh": 1.1581,
    "EUR_per_kWh": 0.10169,
    "EXR": 11.3885,
    "time_start": "2026-02-03T23:00:00+01:00",
    "time_end": "2026-02-04T00:00:00+01:00"
  }
]
