[
  {
    "NOK_per_kWh": 0.67666,
    "EUR_per_kWh": 0.0573,
    "EXR": 11.809,
    "time_start": "2025-12-12T00:00:00+01:00",
    "time_end": "2025-12-12T01:00:00+01:00"
  },
  {
    "NOK_per_kWh": 0.64276,
    "EUR_per_kWh": 0.05443,
    "EXR": 11.809,
    "time_start": "2025-12-12T01:00:00+01:00",
    "time_end": "2025-12-12T02:00:00+01:00"
  },
  {
    "NOK_per_kWh": 0.64749,
    "EUR_per_kWh": 0.05483,
    "EXR": 11.809,
    "time_start": "2025-12-12T02:00:00+01:00",
    "time_end": "2025-12-12T03:00:00+01:00"
  },
  {
    "NOK_per_kWh": 0.70122,
    "EUR_per_kWh": 0.05938,
    "EXR": 11.809,
    "time_start": "2025-12-12T03:00:00+01:00",
    "time_end": "2025-12-12T04:00:00+01:00"
  },
  {
    "NOK_per_kWh": 0.68846,
    "EUR_per_kWh": 0.0583,
    "EXR": 11.809,
    "time_start": "2025-12-12T04:00:00+01:00",
    "time_end": "2025-12-12T05:00:00+01:00"
  },
  {
    "NOK_per_kWh": 0.75778,
    "EUR_per_kWh": 0.06417,
    "EXR": 11.809,
    "time_start": "2025-12-12T05:00:00+01:00",
    "time_end": "2025-12-12T06:00:00+01:00"
  },
  {
    "NOK_per_kWh": 0.92205,
    "EUR_per_kWh": 0.07808,
    "EXR": 11.809,
    "time_start": "2025-12-12T06:00:00+01:00",
    "time_end": "2025-12-12T07:00:00+01:00"
  },
  {
    "NOK_per_kWh": 1.25293,
    "EUR_per_kWh": 0.1061,
    "EXR": 11.809,
    "time_start": "2025-12-12T07:00:00+01:00",
    "time_end": "2025-12-12T08:00:00+01:00"
  },
  {
    "NOK_per_kWh": 1.35036,
    "EUR_per_kWh": 0.11435,
    "EXR": 11.809,
    "time_start": "2025-12-12T08:00:00+01:00",
    "time_end": "2025-12-12T09:00:00+01:00"
  },
  {
    "NOK_per_kWh": 1.36961,
    "EUR_per_kWh": 0.11598,
    "EXR": 11.809,
    "time_start": "2025-12-12T09:00:00+01:00",
    "time_end": "2025-12-12T10:00:00+01:00"
  },
  {
    "NOK_per_kWh": 1.29592,
    "EUR_per_kWh": 0.10974,
    "EXR": 11.809,
    "time_start": "2025-12-12T10:00:00+01:00",
    "time_end": "2025-12-12T11:00:00+01:00"
  },
  {
    "NOK_per_kWh": 1.25742,
    "EUR_per_kWh": 0.10648,
    "EXR": 11.809,
    "time_start": "2025-12-12T11:00:00+01:00",
    "time_end": "2025-12-12T12:00:00+01:00"
  },
  {
    "NOK_per_kWh": 1.19731,
    "EUR_per_kWh": 0.10139,
    "EXR": 11.809,
    "time_start": "2025-12-12T12:00:00+01:00",
    "time_end": "2025-12-12T13:00:00+01:00"
  },
  {
    "NOK_per_kWh": 1.15303,
    "EUR_per_kWh": 0.09764,
    "EXR": 11.809,
    "time_start": "2025-12-12T13:00:00+01:00",
    "time_end": "2025-12-12T14:00:00+01:00"
  },
  {
    "NOK_per_kWh": 1.19354,
    "EUR_per_kWh": 0.10107,
    "EXR": 11.809,
    "time_start": "2025-12-12T14:00:00+01:00",
    "time_end": "2025-12-12T15:00:00+01:00"
  },
  {
    "NOK_per_kWh": 1.24065,
    "EUR_per_kWh": 0.10506,
    "EXR": 11.809,
    "time_start": "2025-12-12T15:00:00+01:00",
    "time_end": "2025-12-12T16:00:00+01:00"
  },
  {
    "NOK_per_kWh": 1.39169,
    "EUR_per_kWh": 0.11785,
    "EXR": 11.809,
    "time_start": "2025-12-12T16:00:00+01:00",
    "time_end": "2025-12-12T17:00:00+01:00"
  },
  {
    "NOK_per_kWh": 1.38059,
    "EUR_per_kWh": 0.11691,
    "EXR": 11.809,
    "time_start": "2025-12-12T17:00:00+01:00",
    "time_end": "2025-12-12T18:00:00+01:00"
  },
  {
    "NOK_per_kWh": 1.24065,
    "EUR_per_kWh": 0.10506,
    "EXR": 11.809,
    "time_start": "2025-12-12T18:00:00+01:00",
    "time_end": "2025-12-12T19:00:00+01:00"
  },
  {
    "NOK_per_kWh": 1.11453,
    "EUR_per_kWh": 0.09438,
    "EXR": 11.809,
    "time_start": "2025-12-12T19:00:00+01:00",
    "time_end": "2025-12-12T20:00:00+01:00"
  },
  {
    "NOK_per_kWh": 0.95192,
    "EUR_per_kWh": 0.08061,
    "EXR": 11.809,
    "time_start": "2025-12-12T20:00:00+01:00",
    "time_end": "2025-12-12T21:00:00+01:00"
  },
  {
    "NOK_per_kWh": 0.79876,
    "EUR_per_kWh": 0.06764,
    "EXR": 11.809,
    "time_start": "2025-12-12T21:00:00+01:00",
    "time_end": "2025-12-12T22:00:00+01:00"
  },
  {
    "NOK_per_kWh": 0.77632,
    "EUR_per_kWh": 0.06574,
    "EXR": 11.809,
    "time_start": "2025-12-12T22:00:00+01:00",
    "time_end": "2025-12-12T23:00:00+01:00"
  },
  {
    "NOK_per_kWh": 0.75743,
    "EUR_per_kWh": 0.06414,
    "EXR": 11.809,
    "time_start": "2025-12-12T23:00:00+01:00",
    "time_end": "2025-12-13T00:00:00+01:00"
  }
]
