[
  {
    "NOK_per_kWh": 1.18882,
    "EUR_per_kWh": 0.10564,
    "EXR": 11.2535,
    "time_start": "2026-02-14T00:00:00+01:00",
    "time_end": "2026-02-14T01:00:00+01:00"
  },
  {
    "NOK_per_kWh": 1.17779,
    "EUR_per_kWh": 0.10466,
    "EXR": 11.2535,
    "time_start": "2026-02-14T01:00:00+01:00",
    "time_end": "2026-02-14T02:00:00+01:00"
  },
  {
    "NOK_per_kWh": 1.1653,
    "EUR_per_kWh": 0.10355,
    "EXR": 11.2535,
    "time_start": "2026-02-14T02:00:00+01:00",
    "time_end": "2026-02-14T03:00:00+01:00"
  },
  {
    "NOK_per_kWh": 1.15663,
    "EUR_per_kWh": 0.10278,
    "EXR": 11.2535,
    "time_start": "2026-02-14T03:00:00+01:00",
    "time_end": "2026-02-14T04:00:00+01:00"
  },
  {
    "NOK_per_kWh": 1.15303,
    "EUR_per_kWh": 0.10246,
    "EXR": 11.2535,
    "time_start": "2026-02-14T04:00:00+01:00",
    "time_end": "2026-02-14T05:00:00+01:00"
  },
  {
    "NOK_per_kWh": 1.13255,
    "EUR_per_kWh": 0.10064,
    "EXR": 11.2535,
    "time_start": "2026-02-14T05:00:00+01:00",
    "time_end": "2026-02-14T06:00:00+01:00"
  },
  {
    "NOK_per_kWh": 1.1671,
    "EUR_per_kWh": 0.10371,
    "EXR": 11.2535,
    "time_start": "2026-02-14T06:00:00+01:00",
    "time_end": "2026-02-14T07:00:00+01:00"
  },
  {
    "NOK_per_kWh": 1.22449,
    "EUR_per_kWh": 0.10881,
    "EXR": 11.2535,
    "time_start": "2026-02-14T07:00:00+01:00",
    "time_end": "2026-02-14T08:00:00+01:00"
  },
  {
    "NOK_per_kWh": 1.32049,
    "EUR_per_kWh": 0.11734,
    "EXR": 11.2535,
    "time_start": "2026-02-14T08:00:00+01:00",
    "time_end": "2026-02-14T09:00:00+01:00"
  },
  {
    "NOK_per_kWh": 1.36505,
    "EUR_per_kWh": 0.1213,
    "EXR": 11.2535,
    "time_start": "2026-02-14T09:00:00+01:00",
    "time_end": "2026-02-14T10:00:00+01:00"
  },
  {
    "NOK_per_kWh": 1.34513,
    "EUR_per_kWh": 0.11953,
    "EXR": 11.2535,
    "time_start": "2026-02-14T10:00:00+01:00",
    "time_end": "2026-02-14T11:00:00+01:00"
  },
  {
    "NOK_per_kWh": 1.23563,
    "EUR_per_kWh": 0.1098,
    "EXR": 11.2535,
    "time_start": "2026-02-14T11:00:00+01:00",
    "time_end": "2026-02-14T12:00:00+01:00"
  },
  {
    "NOK_per_kWh": 1.21335,
    "EUR_per_kWh": 0.10782,
    "EXR": 11.2535,
    "time_start": "2026-02-14T12:00:00+01:00",
    "time_end": "2026-02-14T13:00:00+01:00"
  },
  {
    "NOK_per_kWh": 1.19478,
    "EUR_per_kWh": 0.10617,
    "EXR": 11.2535,
    "time_start": "2026-02-14T13:00:00+01:00",
    "time_end": "2026-02-14T14:00:00+01:00"
  },
  {
    "NOK_per_kWh": 1.1922,
    "EUR_per_kWh": 0.10594,
    "EXR": 11.2535,
    "time_start": "2026-02-14T14:00:00+01:00",
    "time_end": "2026-02-14T15:00:00+01:00"
  },
  {
    "NOK_per_kWh": 1.20502,
    "EUR_per_kWh": 0.10708,
    "EXR": 11.2535,
    "time_start": "2026-02-14T15:00:00+01:00",
    "time_end": "2026-02-14T16:00:00+01:00"
  },
  {
    "NOK_per_kWh": 1.33196,
    "EUR_per_kWh": 0.11836,
    "EXR": 11.2535,
    "time_start": "2026-02-14T16:00:00+01:00",
    "time_end": "2026-02-14T17:00:00+01:00"
  },
  {
    "NOK_per_kWh": 1.44765,
    "EUR_per_kWh": 0.12864,
    "EXR": 11.2535,
    "time_start": "2026-02-14T17:00:00+01:00",
    "time_end": "2026-02-14T18:00:00+01:00"
  },
  {
    "NOK_per_kWh": 1.47398,
    "EUR_per_kWh": 0.13098,
    "EXR": 11.2535,
    "time_start": "2026-02-14T18:00:00+01:00",
    "time_end": "2026-02-14T19:00:00+01:00"
  },
  {
    "NOK_per_kWh": 1.40961,
    "EUR_per_kWh": 0.12526,
    "EXR": 11.2535,
    "time_start": "2026-02-14T19:00:00+01:00",
    "time_end": "2026-02-14T20:00:00+01:00"
  },
  {
    "NOK_per_kWh": 1.34457,
    "EUR_per_kWh": 0.11948,
    "EXR": 11.2535,
    "time_start": "2026-02-14T20:00:00+01:00",
    "time_end": "2026-02-14T21:00:00+01:00"
  },
  {
    "NOK_per_kWh": 1.28695,
    "EUR_per_kWh": 0.11436,
    "EXR": 11.2535,
    "time_start": "2026-02-14T21:00:00+01:00",
    "time_end": "2026-02-14T22:00:00+01:00"
  },
  {
    "NOK_per_kWh": 1.23417,
    "EUR_per_kWh": 0.10967,
    "EXR": 11.2535,
    "time_start": "2026-02-14T22:00:00+01:00",
    "time_end": "2026-02-14T23:00:00+01:00"
  },
  {
    "NOK_per_kWh": 1.14808,
    "EUR_per_kWh": 0.10202,
    "EXR": 11.2535,
    "time_start": "2026-02-14T23:00:00+01:00",
    "time_end": "2026-02-15T00:00:00+01:00"
  }
]
